{
  "0": {
    "日期": 1704067200000,
    "时间": "08:00",
    "地区": "韩国",
    "事件": "韩国12月出口年率(%)",
    "公布": 5.1,
    "预期": 6.6,
    "前值": 7.7,
    "重要性": 1
  },
  "1": {
    "日期": 1704067200000,
    "时间": "08:00",
    "地区": "韩国",
    "事件": "韩国12月贸易帐(亿美元)",
    "公布": 44.8,
    "预期": 62.6,
    "前值": 37.8,
    "重要性": 1
  },
  "2": {
    "日期": 1704067200000,
    "时间": "08:00",
    "地区": "韩国",
    "事件": "韩国12月进口年率(%)",
    "公布": -10.8,
    "预期": -11.4,
    "前值": -11.6,
    "重要性": 1
  },
  "fetchDate": "2024/11/25"
}
